dictionary_wrapper/__init__.py
dictionary_wrapper/clients/_wm_utils.py
dictionary_wrapper/clients/_wordnik_utils.py
dictionary_wrapper/clients/mw_client.py
dictionary_wrapper/clients/mw_client_async.py
dictionary_wrapper/clients/wordnik_client.py
dictionary_wrapper/clients/wordnik_client_async.py
dictionary_wrapper/config.py
dictionary_wrapper/exceptions.py
dictionary_wrapper/models/common_models.py
dictionary_wrapper/models/syn_ant_enum.py
dictionary_wrapper/models/wordnik_models.py
dictionary_wrapper-0.1.4.dist-info/METADATA
dictionary_wrapper-0.1.4.dist-info/WHEEL
dictionary_wrapper-0.1.4.dist-info/RECORD
