Metadata-Version: 2.1
Name: dictionary-wrapper
Version: 0.1.4
Summary: 
Author: adaxiang
Author-email: adaxiang3104@gmail.com
Requires-Python: >=3.12,<4.0
Classifier: Programming Language :: Python :: 3
Classifier: Programming Language :: Python :: 3.12
Requires-Dist: aiohttp (>=3.10.2,<4.0.0)
Requires-Dist: bs4 (>=0.0.2,<0.0.3)
Requires-Dist: english-ipa (==1.0.0)
Requires-Dist: lxml (>=5.2.2,<6.0.0)
Requires-Dist: pydantic (>=2.8.2,<3.0.0)
Requires-Dist: python-dotenv (>=1.0.1,<2.0.0)
